{
  "project_info": {
    "project_number": "661133921309",
    "project_id": "camera-app-dcb26",
    "storage_bucket": "camera-app-dcb26.firebasestorage.app"
  },
  "client": [
    {
      "client_info": {
        "mobilesdk_app_id": "1:661133921309:android:485e406df3aa1f78148af4",
        "android_client_info": {
          "package_name": "com.example.camera_block_app"
        }
      },
      "oauth_client": [],
      "api_key": [
        {
          "current_key": "AIzaSyD9S3lKuj8esYXNz_0PsMLckGe15CUFtsg"
        }
      ],
      "services": {
        "appinvite_service": {
          "other_platform_oauth_client": []
        }
      }
    }
  ],
  "configuration_version": "1"
}